{
  "generated_at": "2026-05-08T16:27:57.501186",
  "short_term": {
    "total": 7,
    "high_importance": 0,
    "by_type": {
      "decision": {
        "count": 5,
        "last": "2026-05-08T16:01:40.276005",
        "recent": [
          "2881.TW buy @ $96.69999694824219 — value評分76.1分",
          "2892.TW buy @ $29.5 — value評分67.0分",
          "2891.TW buy @ $56.400001525878906 — value評分60.9分",
          "2317.TW watch @ $250.0 — value評分55.1分",
          "2882.TW watch @ $80.0 — value評分47.9分"
        ]
      },
      "metric": {
        "count": 1,
        "last": "2026-05-08T16:01:40.282546",
        "recent": [
          "高品質3檔"
        ]
      },
      "observation": {
        "count": 1,
        "last": "2026-05-08T16:01:40.246526",
        "recent": [
          "TW500 value掃描：5檔中 3 檔高品質"
        ]
      }
    },
    "days_covered": 7
  },
  "long_term": {
    "patterns": {
      "total": 0,
      "by_status": {},
      "high_confidence": 0,
      "avg_hit_rate": 0
    },
    "lessons": {
      "total": 0,
      "by_type": {}
    },
    "frameworks": {
      "total": 0
    }
  },
  "working": {
    "active_positions": {
      "total": 0,
      "by_universe": {}
    },
    "watchlist": [],
    "alerts": [],
    "pending_decisions": 0,
    "memory_queue_size": 0
  },
  "distillation": {
    "recent": [],
    "total": 0
  },
  "growth": {
    "avg_per_day_7d": 7.0,
    "prev_avg_7d": 0.0,
    "growth_pct": 0,
    "total_last_7d": 7,
    "total_prev_7d": 0
  },
  "system_last_active": {
    "universe_scanner": "2026-05-08T15:38:29.174700",
    "short_term": "2026-05-08T16:01:40.285170",
    "long_term_patterns": "2026-05-08T15:53:23.054491",
    "long_term_lessons": "2026-05-08T15:53:29.905842"
  },
  "health": {
    "total_memory_entries": 7,
    "long_term_total": 0,
    "distill_queue_size": 0,
    "score": 60,
    "label": "🟡 Good"
  }
}